[{"time":"00:10-15 min.", "bw":197, "so":58, "si":60, "do":3, "di":4, "bus":0},
{"time":"00:15-20 min.", "bw":419, "so":66, "si":67, "do":3, "di":3, "bus":0},
{"time":"00:20-25 min.", "bw":350, "so":72, "si":73, "do":4, "di":3, "bus":0},
{"time":"00:25-30 min.", "bw":382, "so":72, "si":70, "do":5, "di":3, "bus":0},
{"time":"00:30-35 min.", "bw":384, "so":65, "si":64, "do":5, "di":4, "bus":0},
{"time":"00:35-40 min.", "bw":435, "so":64, "si":62, "do":5, "di":4, "bus":0},
{"time":"00:40-45 min.", "bw":407, "so":60, "si":60, "do":4, "di":5, "bus":0},
{"time":"00:45-50 min.", "bw":122, "so":58, "si":60, "do":3, "di":4, "bus":0},
{"time":"00:50-55 min.", "bw":13, "so":56, "si":58, "do":3, "di":4, "bus":0},
{"time":"00:55-60 min.", "bw":5, "so":58, "si":60, "do":2, "di":3, "bus":0},
{"time":"01:00-05 min.", "bw":3, "so":56, "si":56, "do":2, "di":2, "bus":0},
{"time":"01:05-10 min.", "bw":2, "so":57, "si":57, "do":2, "di":2, "bus":0},
{"time":"01:10-15 min.", "bw":2, "so":50, "si":49, "do":3, "di":2, "bus":0},
{"time":"01:15-20 min.", "bw":1, "so":52, "si":51, "do":2, "di":2, "bus":0},
{"time":"01:20-25 min.", "bw":3, "so":51, "si":51, "do":3, "di":2, "bus":0},
{"time":"01:25-30 min.", "bw":9, "so":58, "si":58, "do":3, "di":3, "bus":0},
{"time":"01:30-35 min.", "bw":57, "so":54, "si":53, "do":4, "di":3, "bus":0},
{"time":"01:35-40 min.", "bw":55, "so":53, "si":53, "do":3, "di":3, "bus":0},
{"time":"01:40-45 min.", "bw":51, "so":50, "si":51, "do":2, "di":3, "bus":0},
{"time":"01:45-50 min.", "bw":17, "so":54, "si":56, "do":2, "di":4, "bus":0},
{"time":"01:50-55 min.", "bw":17, "so":54, "si":56, "do":3, "di":4, "bus":0},
{"time":"01:55-60 min.", "bw":15, "so":56, "si":58, "do":3, "di":4, "bus":0},
{"time":"02:00-05 min.", "bw":3, "so":52, "si":53, "do":2, "di":3, "bus":0},
{"time":"02:05-10 min.", "bw":4, "so":52, "si":53, "do":2, "di":3, "bus":0},
{"time":"02:10-15 min.", "bw":3, "so":47, "si":48, "do":2, "di":3, "bus":0},
{"time":"02:15-20 min.", "bw":2, "so":49, "si":49, "do":2, "di":2, "bus":0},
{"time":"02:20-25 min.", "bw":2, "so":49, "si":48, "do":2, "di":2, "bus":0},
{"time":"02:25-30 min.", "bw":1, "so":50, "si":48, "do":2, "di":1, "bus":0},
{"time":"02:30-35 min.", "bw":2, "so":46, "si":44, "do":3, "di":2, "bus":0},
{"time":"02:35-40 min.", "bw":14, "so":45, "si":45, "do":3, "di":3, "bus":0},
{"time":"02:40-45 min.", "bw":14, "so":44, "si":45, "do":3, "di":3, "bus":0},
{"time":"02:45-50 min.", "bw":14, "so":46, "si":48, "do":2, "di":3, "bus":0},
{"time":"02:50-55 min.", "bw":5, "so":46, "si":48, "do":2, "di":3, "bus":0},
{"time":"02:55-60 min.", "bw":5, "so":53, "si":53, "do":3, "di":3, "bus":0},
{"time":"03:00-05 min.", "bw":3, "so":57, "si":56, "do":3, "di":2, "bus":0},
{"time":"03:05-10 min.", "bw":0, "so":57, "si":56, "do":2, "di":1, "bus":0},
{"time":"03:10-15 min.", "bw":0, "so":53, "si":53, "do":2, "di":2, "bus":0},
{"time":"03:15-20 min.", "bw":0, "so":52, "si":52, "do":1, "di":2, "bus":0},
{"time":"03:20-25 min.", "bw":0, "so":51, "si":51, "do":2, "di":2, "bus":0},
{"time":"03:25-30 min.", "bw":0, "so":49, "si":48, "do":2, "di":2, "bus":0},
{"time":"03:30-35 min.", "bw":0, "so":46, "si":45, "do":2, "di":1, "bus":0},
{"time":"03:35-40 min.", "bw":0, "so":44, "si":44, "do":2, "di":1, "bus":0},
{"time":"03:40-45 min.", "bw":0, "so":42, "si":41, "do":1, "di":1, "bus":0},
{"time":"03:45-50 min.", "bw":0, "so":38, "si":38, "do":1, "di":1, "bus":0},
{"time":"03:50-55 min.", "bw":0, "so":41, "si":41, "do":2, "di":2, "bus":0},
{"time":"03:55-60 min.", "bw":0, "so":45, "si":46, "do":2, "di":2, "bus":0},
{"time":"04:00-05 min.", "bw":0, "so":53, "si":54, "do":1, "di":2, "bus":0},
{"time":"04:05-10 min.", "bw":0, "so":51, "si":52, "do":1, "di":2, "bus":0},
{"time":"04:10-15 min.", "bw":1, "so":51, "si":51, "do":2, "di":2, "bus":0},
{"time":"04:15-20 min.", "bw":1, "so":45, "si":46, "do":2, "di":2, "bus":0},
{"time":"04:20-25 min.", "bw":1, "so":47, "si":48, "do":2, "di":3, "bus":0},
{"time":"04:25-30 min.", "bw":1, "so":50, "si":51, "do":2, "di":3, "bus":0},
{"time":"04:30-35 min.", "bw":2, "so":48, "si":49, "do":2, "di":3, "bus":0},
{"time":"04:35-40 min.", "bw":1, "so":47, "si":48, "do":2, "di":3, "bus":0},
{"time":"04:40-45 min.", "bw":1, "so":40, "si":41, "do":1, "di":2, "bus":0},
{"time":"04:45-50 min.", "bw":0, "so":44, "si":44, "do":1, "di":2, "bus":0},
{"time":"04:50-55 min.", "bw":0, "so":43, "si":43, "do":1, "di":1, "bus":0},
{"time":"04:55-60 min.", "bw":2, "so":46, "si":47, "do":2, "di":2, "bus":0},
{"time":"05:00-05 min.", "bw":2, "so":47, "si":48, "do":2, "di":2, "bus":0},
{"time":"05:05-10 min.", "bw":3, "so":48, "si":49, "do":2, "di":3, "bus":0},
{"time":"05:10-15 min.", "bw":24, "so":45, "si":46, "do":3, "di":3, "bus":2},
{"time":"05:15-20 min.", "bw":25, "so":43, "si":43, "do":3, "di":3, "bus":0},
{"time":"05:20-25 min.", "bw":24, "so":44, "si":44, "do":3, "di":3, "bus":0},
{"time":"05:25-30 min.", "bw":2, "so":44, "si":44, "do":2, "di":2, "bus":2},
{"time":"05:30-35 min.", "bw":12, "so":44, "si":44, "do":2, "di":2, "bus":0},
{"time":"05:35-40 min.", "bw":13, "so":43, "si":42, "do":3, "di":2, "bus":2},
{"time":"05:40-45 min.", "bw":15, "so":44, "si":42, "do":3, "di":2, "bus":0},
{"time":"05:45-50 min.", "bw":5, "so":47, "si":44, "do":3, "di":2, "bus":0},
{"time":"05:50-55 min.", "bw":5, "so":50, "si":47, "do":3, "di":2, "bus":2},
{"time":"05:55-60 min.", "bw":6, "so":53, "si":51, "do":3, "di":3, "bus":0},
{"time":"06:00-05 min.", "bw":37, "so":51, "si":51, "do":2, "di":4, "bus":0},
{"time":"06:05-10 min.", "bw":78, "so":51, "si":51, "do":3, "di":3, "bus":2},
{"time":"06:10-15 min.", "bw":75, "so":53, "si":52, "do":3, "di":2, "bus":0},
{"time":"06:15-20 min.", "bw":88, "so":51, "si":48, "do":4, "di":2, "bus":0},
{"time":"06:20-25 min.", "bw":732, "so":50, "si":48, "do":4, "di":2, "bus":1},
{"time":"06:25-30 min.", "bw":851, "so":52, "si":50, "do":4, "di":3, "bus":1},
{"time":"06:30-35 min.", "bw":1691, "so":56, "si":54, "do":5, "di":4, "bus":2},
{"time":"06:35-40 min.", "bw":1166, "so":58, "si":56, "do":5, "di":4, "bus":0},
{"time":"06:40-45 min.", "bw":1832, "so":56, "si":53, "do":5, "di":4, "bus":0},
{"time":"06:45-50 min.", "bw":1429, "so":54, "si":52, "do":5, "di":4, "bus":0},
{"time":"06:50-55 min.", "bw":2696, "so":55, "si":54, "do":5, "di":5, "bus":0},
{"time":"06:55-60 min.", "bw":2147, "so":63, "si":64, "do":5, "di":5, "bus":2},
{"time":"07:00-05 min.", "bw":3046, "so":73, "si":72, "do":7, "di":5, "bus":2},
{"time":"07:05-10 min.", "bw":3338, "so":78, "si":76, "do":7, "di":5, "bus":0},
{"time":"07:10-15 min.", "bw":3188, "so":75, "si":71, "do":7, "di":4, "bus":0},
{"time":"07:15-20 min.", "bw":2850, "so":72, "si":70, "do":6, "di":5, "bus":0},
{"time":"07:20-25 min.", "bw":1898, "so":72, "si":69, "do":6, "di":4, "bus":0},
{"time":"07:25-30 min.", "bw":3439, "so":70, "si":69, "do":6, "di":6, "bus":2},
{"time":"07:30-35 min.", "bw":2713, "so":68, "si":66, "do":5, "di":6, "bus":0},
{"time":"07:35-40 min.", "bw":3524, "so":66, "si":63, "do":6, "di":5, "bus":2},
{"time":"07:40-45 min.", "bw":3517, "so":63, "si":61, "do":7, "di":6, "bus":0},
{"time":"07:45-50 min.", "bw":4027, "so":62, "si":60, "do":8, "di":6, "bus":0},
{"time":"07:50-55 min.", "bw":4116, "so":58, "si":58, "do":7, "di":6, "bus":0},
{"time":"07:55-60 min.", "bw":2908, "so":62, "si":62, "do":6, "di":5, "bus":2},
{"time":"08:00-05 min.", "bw":3531, "so":66, "si":67, "do":6, "di":7, "bus":0},
{"time":"08:05-10 min.", "bw":2362, "so":70, "si":72, "do":6, "di":7, "bus":2},
{"time":"08:10-15 min.", "bw":3334, "so":70, "si":69, "do":7, "di":8, "bus":0},
{"time":"08:15-20 min.", "bw":2035, "so":72, "si":70, "do":7, "di":6, "bus":0},
{"time":"08:20-25 min.", "bw":2098, "so":73, "si":74, "do":6, "di":6, "bus":0},
{"time":"08:25-30 min.", "bw":1484, "so":72, "si":75, "do":6, "di":5, "bus":0},
{"time":"08:30-35 min.", "bw":2362, "so":70, "si":73, "do":5, "di":5, "bus":0},
{"time":"08:35-40 min.", "bw":1809, "so":70, "si":69, "do":5, "di":4, "bus":2},
{"time":"08:40-45 min.", "bw":2185, "so":72, "si":70, "do":5, "di":5, "bus":2},
{"time":"08:45-50 min.", "bw":2767, "so":72, "si":69, "do":6, "di":5, "bus":0},
{"time":"08:50-55 min.", "bw":3508, "so":71, "si":68, "do":8, "di":6, "bus":0},
{"time":"08:55-60 min.", "bw":2885, "so":67, "si":68, "do":8, "di":6, "bus":0},
{"time":"09:00-05 min.", "bw":1930, "so":71, "si":73, "do":6, "di":7, "bus":0},
{"time":"09:05-10 min.", "bw":1702, "so":69, "si":73, "do":4, "di":7, "bus":2},
{"time":"09:10-15 min.", "bw":1776, "so":73, "si":76, "do":4, "di":7, "bus":2},
{"time":"09:15-20 min.", "bw":2128, "so":71, "si":71, "do":6, "di":6, "bus":0},
{"time":"09:20-25 min.", "bw":2395, "so":74, "si":74, "do":6, "di":6, "bus":0},
{"time":"09:25-30 min.", "bw":3245, "so":72, "si":71, "do":6, "di":7, "bus":0},
{"time":"09:30-35 min.", "bw":3262, "so":72, "si":75, "do":5, "di":7, "bus":0},
{"time":"09:35-40 min.", "bw":3628, "so":72, "si":74, "do":7, "di":6, "bus":0},
{"time":"09:40-45 min.", "bw":3611, "so":74, "si":74, "do":7, "di":6, "bus":0},
{"time":"09:45-50 min.", "bw":3143, "so":73, "si":73, "do":7, "di":7, "bus":0},
{"time":"09:50-55 min.", "bw":2194, "so":74, "si":74, "do":5, "di":6, "bus":2},
{"time":"09:55-60 min.", "bw":2331, "so":73, "si":74, "do":5, "di":7, "bus":0},
{"time":"10:00-05 min.", "bw":2620, "so":71, "si":70, "do":6, "di":5, "bus":0},
{"time":"10:05-10 min.", "bw":3396, "so":72, "si":74, "do":7, "di":6, "bus":1},
{"time":"10:10-15 min.", "bw":3409, "so":71, "si":71, "do":7, "di":5, "bus":1},
{"time":"10:15-20 min.", "bw":3381, "so":74, "si":75, "do":6, "di":5, "bus":0},
{"time":"10:20-25 min.", "bw":2851, "so":71, "si":72, "do":5, "di":5, "bus":0},
{"time":"10:25-30 min.", "bw":1697, "so":72, "si":73, "do":4, "di":5, "bus":0},
{"time":"10:30-35 min.", "bw":2671, "so":72, "si":71, "do":4, "di":5, "bus":0},
{"time":"10:35-40 min.", "bw":2714, "so":71, "si":70, "do":5, "di":5, "bus":2},
{"time":"10:40-45 min.", "bw":3079, "so":72, "si":71, "do":7, "di":5, "bus":0},
{"time":"10:45-50 min.", "bw":2136, "so":74, "si":72, "do":7, "di":5, "bus":0},
{"time":"10:50-55 min.", "bw":3244, "so":75, "si":72, "do":8, "di":6, "bus":0},
{"time":"10:55-60 min.", "bw":2853, "so":76, "si":74, "do":7, "di":6, "bus":0},
{"time":"11:00-05 min.", "bw":2495, "so":75, "si":73, "do":6, "di":5, "bus":0},
{"time":"11:05-10 min.", "bw":1620, "so":75, "si":74, "do":4, "di":5, "bus":0},
{"time":"11:10-15 min.", "bw":1908, "so":70, "si":70, "do":4, "di":5, "bus":2},
{"time":"11:15-20 min.", "bw":2055, "so":67, "si":70, "do":6, "di":7, "bus":2},
{"time":"11:20-25 min.", "bw":2102, "so":69, "si":70, "do":7, "di":5, "bus":0},
{"time":"11:25-30 min.", "bw":3225, "so":73, "si":73, "do":8, "di":6, "bus":0},
{"time":"11:30-35 min.", "bw":3841, "so":75, "si":74, "do":8, "di":6, "bus":0},
{"time":"11:35-40 min.", "bw":4122, "so":74, "si":74, "do":8, "di":7, "bus":0},
{"time":"11:40-45 min.", "bw":4231, "so":72, "si":72, "do":7, "di":7, "bus":0},
{"time":"11:45-50 min.", "bw":3452, "so":73, "si":73, "do":7, "di":7, "bus":0},
{"time":"11:50-55 min.", "bw":3263, "so":76, "si":75, "do":6, "di":6, "bus":0},
{"time":"11:55-60 min.", "bw":1981, "so":79, "si":80, "do":5, "di":6, "bus":1},
{"time":"12:00-05 min.", "bw":2986, "so":80, "si":82, "do":6, "di":6, "bus":1},
{"time":"12:05-10 min.", "bw":3463, "so":81, "si":86, "do":6, "di":7, "bus":0},
{"time":"12:10-15 min.", "bw":4780, "so":84, "si":86, "do":7, "di":7, "bus":2},
{"time":"12:15-20 min.", "bw":4358, "so":81, "si":82, "do":7, "di":7, "bus":0},
{"time":"12:20-25 min.", "bw":4535, "so":78, "si":79, "do":6, "di":8, "bus":0},
{"time":"12:25-30 min.", "bw":4115, "so":78, "si":80, "do":6, "di":8, "bus":0},
{"time":"12:30-35 min.", "bw":4703, "so":88, "si":87, "do":7, "di":7, "bus":0},
{"time":"12:35-40 min.", "bw":3733, "so":93, "si":90, "do":7, "di":5, "bus":1},
{"time":"12:40-45 min.", "bw":3864, "so":92, "si":87, "do":7, "di":5, "bus":1},
{"time":"12:45-50 min.", "bw":3840, "so":84, "si":81, "do":7, "di":5, "bus":0},
{"time":"12:50-55 min.", "bw":4619, "so":80, "si":80, "do":7, "di":6, "bus":0},
{"time":"12:55-60 min.", "bw":4279, "so":80, "si":81, "do":7, "di":6, "bus":0},
{"time":"13:00-05 min.", "bw":4210, "so":79, "si":79, "do":6, "di":6, "bus":0},
{"time":"13:05-10 min.", "bw":4110, "so":78, "si":76, "do":7, "di":6, "bus":0},
{"time":"13:10-15 min.", "bw":3672, "so":74, "si":75, "do":6, "di":7, "bus":2},
{"time":"13:15-20 min.", "bw":3784, "so":75, "si":77, "do":6, "di":7, "bus":0},
{"time":"13:20-25 min.", "bw":3976, "so":74, "si":79, "do":6, "di":8, "bus":2},
{"time":"13:25-30 min.", "bw":3602, "so":77, "si":80, "do":5, "di":8, "bus":0},
{"time":"13:30-35 min.", "bw":2983, "so":77, "si":77, "do":6, "di":7, "bus":0},
{"time":"13:35-40 min.", "bw":3479, "so":82, "si":82, "do":6, "di":7, "bus":0},
{"time":"13:40-45 min.", "bw":3746, "so":85, "si":84, "do":6, "di":7, "bus":0},
{"time":"13:45-50 min.", "bw":3339, "so":91, "si":90, "do":6, "di":8, "bus":0},
{"time":"13:50-55 min.", "bw":2565, "so":87, "si":87, "do":6, "di":8, "bus":0},
{"time":"13:55-60 min.", "bw":2514, "so":88, "si":86, "do":7, "di":7, "bus":0},
{"time":"14:00-05 min.", "bw":2585, "so":87, "si":84, "do":7, "di":7, "bus":2},
{"time":"14:05-10 min.", "bw":2391, "so":86, "si":87, "do":6, "di":7, "bus":0},
{"time":"14:10-15 min.", "bw":2970, "so":86, "si":86, "do":7, "di":8, "bus":1},
{"time":"14:15-20 min.", "bw":3659, "so":87, "si":88, "do":7, "di":8, "bus":1},
{"time":"14:20-25 min.", "bw":3235, "so":90, "si":88, "do":7, "di":6, "bus":0},
{"time":"14:25-30 min.", "bw":3240, "so":88, "si":89, "do":6, "di":7, "bus":0},
{"time":"14:30-35 min.", "bw":2589, "so":87, "si":86, "do":6, "di":6, "bus":0},
{"time":"14:35-40 min.", "bw":2399, "so":89, "si":90, "do":6, "di":6, "bus":0},
{"time":"14:40-45 min.", "bw":2828, "so":93, "si":94, "do":6, "di":6, "bus":0},
{"time":"14:45-50 min.", "bw":3331, "so":99, "si":102, "do":6, "di":8, "bus":0},
{"time":"14:50-55 min.", "bw":4139, "so":100, "si":100, "do":7, "di":8, "bus":2},
{"time":"14:55-60 min.", "bw":3079, "so":96, "si":94, "do":8, "di":6, "bus":0},
{"time":"15:00-05 min.", "bw":1997, "so":88, "si":90, "do":7, "di":6, "bus":0},
{"time":"15:05-10 min.", "bw":2278, "so":89, "si":88, "do":7, "di":6, "bus":0},
{"time":"15:10-15 min.", "bw":3130, "so":94, "si":97, "do":6, "di":8, "bus":0},
{"time":"15:15-20 min.", "bw":4074, "so":97, "si":99, "do":8, "di":8, "bus":0},
{"time":"15:20-25 min.", "bw":3219, "so":92, "si":97, "do":6, "di":8, "bus":2},
{"time":"15:25-30 min.", "bw":3386, "so":92, "si":92, "do":8, "di":6, "bus":0},
{"time":"15:30-35 min.", "bw":2943, "so":90, "si":90, "do":8, "di":5, "bus":2},
{"time":"15:35-40 min.", "bw":4846, "so":92, "si":92, "do":8, "di":6, "bus":0},
{"time":"15:40-45 min.", "bw":3491, "so":93, "si":96, "do":6, "di":8, "bus":0},
{"time":"15:45-50 min.", "bw":3710, "so":96, "si":97, "do":6, "di":8, "bus":0},
{"time":"15:50-55 min.", "bw":1694, "so":103, "si":102, "do":5, "di":7, "bus":2},
{"time":"15:55-60 min.", "bw":2488, "so":105, "si":103, "do":6, "di":6, "bus":0},
{"time":"16:00-05 min.", "bw":3005, "so":110, "si":110, "do":5, "di":7, "bus":0},
{"time":"16:05-10 min.", "bw":3086, "so":111, "si":112, "do":6, "di":7, "bus":0},
{"time":"16:10-15 min.", "bw":3094, "so":108, "si":109, "do":7, "di":7, "bus":0},
{"time":"16:15-20 min.", "bw":3131, "so":105, "si":106, "do":7, "di":6, "bus":2},
{"time":"16:20-25 min.", "bw":2907, "so":101, "si":101, "do":7, "di":5, "bus":2},
{"time":"16:25-30 min.", "bw":2921, "so":102, "si":101, "do":7, "di":6, "bus":0},
{"time":"16:30-35 min.", "bw":3415, "so":100, "si":99, "do":8, "di":7, "bus":0},
{"time":"16:35-40 min.", "bw":4346, "so":100, "si":98, "do":9, "di":7, "bus":0},
{"time":"16:40-45 min.", "bw":5377, "so":106, "si":101, "do":10, "di":6, "bus":0},
{"time":"16:45-50 min.", "bw":5334, "so":105, "si":100, "do":10, "di":7, "bus":0},
{"time":"16:50-55 min.", "bw":5526, "so":107, "si":104, "do":10, "di":8, "bus":2},
{"time":"16:55-60 min.", "bw":3822, "so":99, "si":103, "do":7, "di":8, "bus":2},
{"time":"17:00-05 min.", "bw":3936, "so":102, "si":103, "do":7, "di":7, "bus":0},
{"time":"17:05-10 min.", "bw":3187, "so":103, "si":104, "do":6, "di":7, "bus":0},
{"time":"17:10-15 min.", "bw":4083, "so":108, "si":106, "do":7, "di":7, "bus":0},
{"time":"17:15-20 min.", "bw":3390, "so":107, "si":105, "do":8, "di":7, "bus":0},
{"time":"17:20-25 min.", "bw":3527, "so":109, "si":107, "do":8, "di":8, "bus":2},
{"time":"17:25-30 min.", "bw":2825, "so":108, "si":107, "do":7, "di":7, "bus":0},
{"time":"17:30-35 min.", "bw":3747, "so":110, "si":112, "do":7, "di":9, "bus":2},
{"time":"17:35-40 min.", "bw":4979, "so":104, "si":105, "do":8, "di":9, "bus":0},
{"time":"17:40-45 min.", "bw":5004, "so":102, "si":102, "do":8, "di":9, "bus":0},
{"time":"17:45-50 min.", "bw":4244, "so":103, "si":104, "do":7, "di":8, "bus":1},
{"time":"17:50-55 min.", "bw":3392, "so":110, "si":107, "do":8, "di":7, "bus":1},
{"time":"17:55-60 min.", "bw":3949, "so":112, "si":115, "do":7, "di":9, "bus":0},
{"time":"18:00-05 min.", "bw":3407, "so":112, "si":114, "do":8, "di":9, "bus":1},
{"time":"18:05-10 min.", "bw":4311, "so":119, "si":122, "do":8, "di":10, "bus":1},
{"time":"18:10-15 min.", "bw":3754, "so":124, "si":123, "do":9, "di":8, "bus":0},
{"time":"18:15-20 min.", "bw":3184, "so":124, "si":122, "do":8, "di":7, "bus":0},
{"time":"18:20-25 min.", "bw":1648, "so":120, "si":120, "do":7, "di":5, "bus":2},
{"time":"18:25-30 min.", "bw":3098, "so":124, "si":122, "do":7, "di":7, "bus":0},
{"time":"18:30-35 min.", "bw":3779, "so":126, "si":125, "do":8, "di":8, "bus":0},
{"time":"18:35-40 min.", "bw":4169, "so":127, "si":129, "do":8, "di":9, "bus":0},
{"time":"18:40-45 min.", "bw":2999, "so":126, "si":128, "do":7, "di":8, "bus":0},
{"time":"18:45-50 min.", "bw":3466, "so":129, "si":132, "do":8, "di":8, "bus":0},
{"time":"18:50-55 min.", "bw":3204, "so":124, "si":124, "do":8, "di":8, "bus":0},
{"time":"18:55-60 min.", "bw":3261, "so":120, "si":124, "do":7, "di":8, "bus":2},
{"time":"19:00-05 min.", "bw":2920, "so":113, "si":115, "do":6, "di":7, "bus":0},
{"time":"19:05-10 min.", "bw":2993, "so":107, "si":109, "do":5, "di":6, "bus":0},
{"time":"19:10-15 min.", "bw":3261, "so":109, "si":106, "do":6, "di":6, "bus":2},
{"time":"19:15-20 min.", "bw":3693, "so":114, "si":114, "do":7, "di":7, "bus":0},
{"time":"19:20-25 min.", "bw":3857, "so":123, "si":121, "do":8, "di":7, "bus":0},
{"time":"19:25-30 min.", "bw":4865, "so":122, "si":122, "do":8, "di":8, "bus":0},
{"time":"19:30-35 min.", "bw":4282, "so":118, "si":116, "do":8, "di":7, "bus":0},
{"time":"19:35-40 min.", "bw":3794, "so":117, "si":116, "do":8, "di":8, "bus":0},
{"time":"19:40-45 min.", "bw":2850, "so":113, "si":113, "do":8, "di":7, "bus":2},
{"time":"19:45-50 min.", "bw":2661, "so":112, "si":114, "do":6, "di":8, "bus":0},
{"time":"19:50-55 min.", "bw":3855, "so":114, "si":115, "do":8, "di":8, "bus":0},
{"time":"19:55-60 min.", "bw":2613, "so":118, "si":117, "do":7, "di":6, "bus":0},
{"time":"20:00-05 min.", "bw":3061, "so":116, "si":116, "do":7, "di":6, "bus":0},
{"time":"20:05-10 min.", "bw":2527, "so":109, "si":112, "do":5, "di":6, "bus":0},
{"time":"20:10-15 min.", "bw":3374, "so":106, "si":112, "do":5, "di":7, "bus":0},
{"time":"20:15-20 min.", "bw":3596, "so":112, "si":116, "do":5, "di":6, "bus":4},
{"time":"20:20-25 min.", "bw":4052, "so":114, "si":116, "do":6, "di":6, "bus":0},
{"time":"20:25-30 min.", "bw":5423, "so":115, "si":113, "do":7, "di":6, "bus":0},
{"time":"20:30-35 min.", "bw":5458, "so":111, "si":108, "do":8, "di":6, "bus":0},
{"time":"20:35-40 min.", "bw":4619, "so":115, "si":112, "do":8, "di":6, "bus":0},
{"time":"20:40-45 min.", "bw":3535, "so":113, "si":111, "do":7, "di":5, "bus":0},
{"time":"20:45-50 min.", "bw":2814, "so":112, "si":112, "do":6, "di":5, "bus":0},
{"time":"20:50-55 min.", "bw":2339, "so":105, "si":108, "do":4, "di":5, "bus":0},
{"time":"20:55-60 min.", "bw":2253, "so":106, "si":107, "do":4, "di":5, "bus":0},
{"time":"21:00-05 min.", "bw":3400, "so":107, "si":108, "do":4, "di":5, "bus":0},
{"time":"21:05-10 min.", "bw":4204, "so":110, "si":111, "do":5, "di":6, "bus":0},
{"time":"21:10-15 min.", "bw":4822, "so":110, "si":113, "do":5, "di":7, "bus":2},
{"time":"21:15-20 min.", "bw":4573, "so":115, "si":116, "do":6, "di":7, "bus":0},
{"time":"21:20-25 min.", "bw":4453, "so":114, "si":113, "do":6, "di":7, "bus":2},
{"time":"21:25-30 min.", "bw":3764, "so":110, "si":111, "do":6, "di":6, "bus":0},
{"time":"21:30-35 min.", "bw":2946, "so":104, "si":108, "do":4, "di":6, "bus":0},
{"time":"21:35-40 min.", "bw":2785, "so":103, "si":107, "do":5, "di":7, "bus":0},
{"time":"21:40-45 min.", "bw":2185, "so":106, "si":106, "do":5, "di":7, "bus":0},
{"time":"21:45-50 min.", "bw":2375, "so":102, "si":102, "do":5, "di":7, "bus":0},
{"time":"21:50-55 min.", "bw":2168, "so":98, "si":98, "do":5, "di":6, "bus":0},
{"time":"21:55-60 min.", "bw":1753, "so":96, "si":94, "do":4, "di":6, "bus":0},
{"time":"22:00-05 min.", "bw":2476, "so":97, "si":96, "do":5, "di":7, "bus":0},
{"time":"22:05-10 min.", "bw":2471, "so":96, "si":95, "do":6, "di":6, "bus":2},
{"time":"22:10-15 min.", "bw":2748, "so":91, "si":92, "do":5, "di":6, "bus":0},
{"time":"22:15-20 min.", "bw":1314, "so":92, "si":94, "do":5, "di":6, "bus":0},
{"time":"22:20-25 min.", "bw":1022, "so":94, "si":95, "do":3, "di":6, "bus":0},
{"time":"22:25-30 min.", "bw":1045, "so":96, "si":98, "do":5, "di":6, "bus":0},
{"time":"22:30-35 min.", "bw":930, "so":94, "si":93, "do":6, "di":4, "bus":0},
{"time":"22:35-40 min.", "bw":1436, "so":92, "si":93, "do":6, "di":3, "bus":3},
{"time":"22:40-45 min.", "bw":1753, "so":96, "si":96, "do":5, "di":4, "bus":1},
{"time":"22:45-50 min.", "bw":1863, "so":92, "si":94, "do":4, "di":5, "bus":0},
{"time":"22:50-55 min.", "bw":1760, "so":92, "si":94, "do":4, "di":6, "bus":0},
{"time":"22:55-60 min.", "bw":1130, "so":90, "si":93, "do":4, "di":5, "bus":0},
{"time":"23:00-05 min.", "bw":856, "so":97, "si":98, "do":4, "di":4, "bus":0},
{"time":"23:05-10 min.", "bw":591, "so":91, "si":93, "do":4, "di":4, "bus":0},
{"time":"23:10-15 min.", "bw":511, "so":88, "si":88, "do":4, "di":4, "bus":0},
{"time":"23:15-20 min.", "bw":1176, "so":82, "si":84, "do":5, "di":5, "bus":0},
{"time":"23:20-25 min.", "bw":1519, "so":83, "si":84, "do":5, "di":5, "bus":0},
{"time":"23:25-30 min.", "bw":1723, "so":83, "si":86, "do":4, "di":6, "bus":2},
{"time":"23:30-35 min.", "bw":1477, "so":85, "si":87, "do":4, "di":5, "bus":0},
{"time":"23:35-40 min.", "bw":732, "so":84, "si":84, "do":4, "di":5, "bus":0},
{"time":"23:40-45 min.", "bw":519, "so":68, "si":67, "do":3, "di":4, "bus":0},
{"time":"23:45-50 min.", "bw":4, "so":39, "si":38, "do":2, "di":2, "bus":0},
{"time":"23:50-55 min.", "bw":0, "so":14, "si":15, "do":1, "di":2, "bus":0},
{"time":"23:55-60 min.", "bw":0, "so":3, "si":3, "do":1, "di":1, "bus":0}]
